{
  "parent": "block/block",
  "elements": [
    { "from": [ 0.8, 0, 8 ],
      "to": [ 15.2, 16, 8 ],
      "shade": false,
      "rotation": { "origin": [ 8, 8, 8 ], "axis": "y", "angle": 45, "rescale": "true" },
      "faces": {
        "north": { "uv": [ 0, 0, 16, 16 ], "texture": "#blossom" }
      }
    },
    { "from": [ 0.8, 0, 8 ],
      "to": [ 15.2, 16, 8 ],
      "shade": false,
      "rotation": { "origin": [ 8, 8, 8 ], "axis": "y", "angle": 45, "rescale": "true" },
      "faces": {
        "south": { "uv": [ 0, 0, 16, 16 ], "texture": "#blossom" }
      }
    },
    { "from": [ 8, 0, 0.8 ],
      "to": [ 8, 16, 15.2 ],
      "shade": false,
      "rotation": { "origin": [ 8, 8, 8 ], "axis": "y", "angle": 45, "rescale": "true" },
      "faces": {
        "east": { "uv": [ 0, 0, 16, 16 ], "texture": "#blossom" }
      }
    },
    { "from": [ 8, 0, 0.8 ],
      "to": [ 8, 16, 15.2 ],
      "shade": false,
      "rotation": { "origin": [ 8, 8, 8 ], "axis": "y", "angle": 45, "rescale": "true" },
      "faces": {
        "west": { "uv": [ 0, 0, 16, 16 ], "texture": "#blossom" }
      }
    },
    { "from": [ 3, 8, 3 ],
      "to": [ 13, 8, 13 ],
      "faces": {
        "up":   { "uv": [ 3, 3, 13, 13 ], "texture": "#top-thorns" }
      }
    },
    { "from": [ 3, 8, 3 ],
      "to": [ 13, 8, 13 ],
      "faces": {
        "up":   { "uv": [ 3, 3, 13, 13 ], "texture": "#top-body", "tintindex": 0 }
      }
    },
    { "from": [ 3, 0, 4 ],
      "to": [ 13, 9, 4 ],
      "faces": {
        "north": { "uv": [ 3, 3, 13, 12 ], "texture": "#side-thorns" }
      }
    },
    { "from": [ 3, 0, 12 ],
      "to": [ 13, 9, 12 ],
      "faces": {
        "north": { "uv": [ 3, 3, 13, 12 ], "texture": "#side-thorns" }
      }
    },
    { "from": [ 3, 0, 4 ],
      "to": [ 13, 9, 4 ],
      "faces": {
        "south": { "uv": [ 3, 3, 13, 12 ], "texture": "#side-thorns" }
      }
    },
    { "from": [ 3, 0, 12 ],
      "to": [ 13, 9, 12 ],
      "faces": {
        "south": { "uv": [ 3, 3, 13, 12 ], "texture": "#side-thorns" }
      }
    },
    { "from": [ 4, 0, 3 ],
      "to": [ 4, 9, 13 ],
      "faces": {
        "east": { "uv": [ 3, 3, 13, 12 ], "texture": "#side-thorns" }
      }
    },
    { "from": [ 12, 0, 3 ],
      "to": [ 12, 9, 13 ],
      "faces": {
        "east": { "uv": [ 3, 3, 13, 12 ], "texture": "#side-thorns" }
      }
    },
    { "from": [ 4, 0, 3 ],
      "to": [ 4, 9, 13 ],
      "faces": {
        "west": { "uv": [ 3, 3, 13, 12 ], "texture": "#side-thorns" }
      }
    },
    { "from": [ 12, 0, 3 ],
      "to": [ 12, 9, 13 ],
      "faces": {
        "west": { "uv": [ 3, 3, 13, 12 ], "texture": "#side-thorns" }
      }
    },
    { "from": [ 3, 0, 4 ],
      "to": [ 13, 9, 4 ],
      "faces": {
        "north": { "uv": [ 3, 3, 13, 12 ], "texture": "#side-body", "tintindex": 0 }
      }
    },
    { "from": [ 3, 0, 12 ],
      "to": [ 13, 9, 12 ],
      "faces": {
        "south": { "uv": [ 3, 3, 13, 12 ], "texture": "#side-body", "tintindex": 0 }
      }
    },
    { "from": [ 12, 0, 3 ],
      "to": [ 12, 9, 13 ],
      "faces": {
        "east": { "uv": [ 3, 3, 13, 12 ], "texture": "#side-body", "tintindex": 0 }
      }
    },
    { "from": [ 4, 0, 3 ],
      "to": [ 4, 9, 13 ],
      "faces": {
        "west": { "uv": [ 3, 3, 13, 12 ], "texture": "#side-body", "tintindex": 0 }
      }
    },
    { "from": [ 4, 0, 4 ],
      "to": [ 12, 0, 12 ],
      "faces": {
        "down": { "uv": [ 4, 4, 12, 12 ], "texture": "#bottom-outer", "tintindex": 0 }
      }
    },
    { "from": [ 4, 0, 4 ],
      "to": [ 12, 0, 12 ],
      "faces": {
        "down": { "uv": [ 4, 4, 12, 12 ], "texture": "#bottom-inner" }
      }
    }
  ],
  "textures": {
    "blossom": "floralis:blocks/crop/crop/cactus/blossom/cyan/4",
    "top-thorns": "floralis:blocks/crop/crop/cactus/top/thorns/4",
    "top-body": "floralis:blocks/crop/crop/cactus/top/body/4",
    "side-thorns": "floralis:blocks/crop/crop/cactus/side/thorns/4",
    "side-body": "floralis:blocks/crop/crop/cactus/side/body/4",
    "bottom-outer": "floralis:blocks/crop/crop/cactus/bottom/outer/4",
    "bottom-inner": "floralis:blocks/crop/crop/cactus/bottom/inner/4",
    "particle": "floralis:blocks/crop/crop/cactus/top/body/4"
  }
}